sparkflint-1.0.1.data/scripts/sparkflint
sparkflintcli/__init__.py
sparkflintcli/main.py
sparkflintcli/commands/__init__.py
sparkflintcli/commands/add.py
sparkflintcli/commands/config.py
sparkflintcli/commands/init.py
sparkflintcli/commands/kill.py
sparkflintcli/commands/list.py
sparkflintcli/commands/logs.py
sparkflintcli/commands/open.py
sparkflintcli/commands/remove.py
sparkflintcli/commands/run.py
sparkflintcli/commands/schedule.py
sparkflintcli/commands/set.py
sparkflintcli/commands/show.py
sparkflintcli/commands/ssh.py
sparkflintcli/commands/status.py
sparkflintcli/commands/test.py
sparkflintcli/config/__init__.py
sparkflintcli/config/constants.py
sparkflintcli/core/__init__.py
sparkflintcli/core/context.py
sparkflintcli/core/views.py
sparkflintcli/core/controllers/__init__.py
sparkflintcli/core/controllers/app_controller.py
sparkflintcli/core/controllers/auth_controller.py
sparkflintcli/core/controllers/config_controller.py
sparkflintcli/core/controllers/dag_controller.py
sparkflintcli/core/controllers/host_controller.py
sparkflintcli/core/controllers/init_controller.py
sparkflintcli/core/controllers/pipeline_controller.py
sparkflintcli/core/controllers/ssh_controller.py
sparkflintcli/core/controllers/view_controller.py
sparkflintcli/core/models/__init__.py
sparkflintcli/core/models/app_model.py
sparkflintcli/core/models/config_model.py
sparkflintcli/core/models/host_model.py
sparkflintcli/core/models/pipeline_model.py
sparkflintcli/core/models/ssh_model.py
sparkflintcli/core/models/view_model.py
sparkflintcli/core/services/__init__.py
sparkflintcli/core/services/app_service.py
sparkflintcli/core/services/auth_service.py
sparkflintcli/core/services/config_service.py
sparkflintcli/core/services/host_service.py
sparkflintcli/core/services/pipeline_service.py
sparkflintcli/core/services/ssh_service.py
sparkflintcli/core/services/view_service.py
sparkflintcli/core/ui/__init__.py
sparkflintcli/core/ui/app_ui.py
sparkflintcli/core/ui/host_ui.py
sparkflint-1.0.1.dist-info/METADATA
sparkflint-1.0.1.dist-info/WHEEL
sparkflint-1.0.1.dist-info/entry_points.txt
sparkflint-1.0.1.dist-info/top_level.txt
sparkflint-1.0.1.dist-info/RECORD
