Metadata-Version: 2.4
Name: sparkflint
Version: 1.0.1
Summary: SparkFlintCLI facilita a gestão de aplicações Apache Spark em ambientes remotos.
Home-page: https://github.com/RibeiroWiliam/sparkflint-cli
Author: Wiliam Ribeiro
Author-email: wiliamribeiro.tj@gmail.com
Classifier: Programming Language :: Python :: 3
Classifier: License :: OSI Approved :: MIT License
Requires-Dist: typer[all]
Requires-Dist: requests[all]
Requires-Dist: rich
Requires-Dist: toml
Requires-Dist: cryptography
Dynamic: author
Dynamic: author-email
Dynamic: classifier
Dynamic: description
Dynamic: description-content-type
Dynamic: home-page
Dynamic: requires-dist
Dynamic: summary
